{
  "decription": {
    "embed": "normalized word vectors",
    "if_masking": "given labels will be represented differently",
    "mask": "could be: bin, scalable or beans",
    "labels_values": "list of all possible label values",
    "beans_num": "number of beans if mask = beans"
  },
  "main_configuration": {
    "data_sets": {
      "index":"/home/thiziri/Documents/DOCTORAT/COLLECTION/Indri_index/AP88",
      "query_maxlen": 10,
      "doc_maxlen": 1000,
      "vocab_size": 139489,
      "embed_size": 100,
      "embed": "/home/thiziri/Desktop/embed_norm",
      "labels": "/home/thiziri/Desktop/labelers",
      "labelers_num": 2,
      "train_queries":"/home/thiziri/Desktop/test_queries.txt",
      "test_queries":"",
      "if_masking":true,
      "mask": "bin",
      "labels_values": [0,1,2,3],
      "beans_num": 0
    },
    "model": {
      "parameters": {
        "q_activation": "softmax",
        "d_activation": "softmax",
        "hidden_activation": "softmax",
        "output_activation": "softplus",
        "optimizer": "adam",
        "num_layers": 3,
        "layers_size": [
          10,
          8,
          5
        ],
        "regularisation": "BatchNormalization, dropout ..."
      },
      "train": {
        "train_embed": false,
        "loss_function": "binary_crossentropy",
        "metrics": [
          "acc"
        ],
        "batch_size": 5,
        "epochs": 1,
        "verbose":1,
        "shuffle": false,
        "weights": "",
        "train_details": ""
      },
      "test":{}
    }
  }
}